volexity/gittoolfetcher/__init__.py
volexity/gittoolfetcher/_version.py
volexity/gittoolfetcher/cli.py
volexity/gittoolfetcher/git_tool_fetcher.py
volexity/gittoolfetcher/plaintext_stream_handler.py
volexity/gittoolfetcher/py.typed
volexity/gittoolfetcher/models/__init__.py
volexity/gittoolfetcher/models/cli_arguments.py
volexity/gittoolfetcher/models/tool_management_result.py
volexity/gittoolfetcher/models/tool_process_error.py
gittoolfetcher-1.2.1.dist-info/METADATA
gittoolfetcher-1.2.1.dist-info/WHEEL
gittoolfetcher-1.2.1.dist-info/entry_points.txt
gittoolfetcher-1.2.1.dist-info/licenses/LICENSE.md
gittoolfetcher-1.2.1.dist-info/RECORD
