Metadata-Version: 2.4
Name: gittoolfetcher
Version: 1.2.1
Summary: A git management tool, making it easy to install and use multiple concurent version of a same project.
Project-URL: Documentation, https://github.com/volexity/gittoolfetcher/blob/main/README.md
Project-URL: Issues, https://github.com/volexity/gittoolfetcher/issues
Project-URL: Source, https://github.com/volexity/gittoolfetcher
Author-email: Killian Raimbaud <kraimbaud@volexity.com>
License-File: LICENSE.md
Classifier: Programming Language :: Python
Classifier: Programming Language :: Python :: 3.10
Classifier: Programming Language :: Python :: 3.11
Classifier: Programming Language :: Python :: 3.12
Classifier: Programming Language :: Python :: 3.13
Classifier: Programming Language :: Python :: Implementation :: CPython
Classifier: Programming Language :: Python :: Implementation :: PyPy
Requires-Python: >=3.10
Requires-Dist: multiprocess~=0.70.18
Requires-Dist: requests~=2.32.3
